paper_qa_docling-2026.1.5.dist-info/licenses/LICENSE
paperqa_docling/__init__.py
paperqa_docling/py.typed
paperqa_docling/reader.py
paperqa_docling/version.py
paper_qa_docling-2026.1.5.dist-info/METADATA
paper_qa_docling-2026.1.5.dist-info/WHEEL
paper_qa_docling-2026.1.5.dist-info/top_level.txt
paper_qa_docling-2026.1.5.dist-info/RECORD
